{
    "LevelType": "GET_BIG",
    "WorldShape": "RECTANGLE",
    "Title": "New Neighbors",
    "Mission": "Harvest their light",
    "Tips":[
        ],
    "Background": "data/levels/level4/bg.jpg",
    "Music": "data/audio/music/colorful.ogg",
    "MinZoom": 3,
    "MaxZoom": 6,
    "DefZoom": 6,
    "PlayerColor": "WHITE",
    "PlayerRadius": 5,
    "PlayerCritRadiusMult": 3,
    "PlayerSpawn": [
        0,
        -10
        ],
    "Ambience": [
        0.2,
        0.1,
        0.5,
        0.3
        ],
    "WinConditions": [
        "NoOtherLumis",
        ],
    "ParticleEffect": {
            "Path": "",
            "x": 0,
            "y": 0,
        },
    "Enemies": {
        "Drifter": {
            "EnemyType": "1",
            "Color": "PURPLE",
            "x": -170,
            "y": 50,
            "Radius": 7,
            "Direction": 0,
            "AngularVelocity": 0,
            "CritRadiusMult": 1.3,
            "Velocity": 200
        },
        "Drifter": {
            "EnemyType": "1",
            "Color": "PURPLE",
            "x": 150,
            "y": 50,
            "Radius": 8,
            "Direction": 3.14159,
            "AngularVelocity": 0,
            "CritRadiusMult": 1.3,
            "Velocity": 200
        },
        "Drifter": {
            "EnemyType": "1",
            "Color": "RED",
            "x": -175,
            "y":  10,
            "Radius": 7,
            "Direction": 0,
            "AngularVelocity": 0,
            "CritRadiusMult": 1.3,
            "Velocity": 250
        },
        "Drifter": {
            "EnemyType": "1",
            "Color": "RED",
            "x": 175,
            "y": 10,
            "Radius": 8,
            "Direction": 3.14159,
            "AngularVelocity": 0,
            "CritRadiusMult": 1.3,
            "Velocity": 250
        },
        "Drifter": {
            "EnemyType": "1",
            "Color": "GREEN",
            "x": -170,
            "y": 80,
            "Radius": 10,
            "Direction": 0,
            "AngularVelocity": 0,
            "CritRadiusMult": 1.4,
            "Velocity": 100
        },
        "Drifter": {
            "EnemyType": "1",
            "Color": "GREEN",
            "x": 170,
            "y": 80,
            "Radius": 10,
            "Direction": 3.14159,
            "AngularVelocity": 0,
            "CritRadiusMult": 1.2,
            "Velocity": 175
        },
       "Drifter": {
            "EnemyType": "1",
            "Color": "YELLOW",
            "x": -5,
            "y":  -210,
            "Radius": 7,
            "Direction": 3.2,
            "AngularVelocity": -1,
            "CritRadiusMult": 1.3,
            "Velocity": 70
        },
        "Drifter": {
            "EnemyType": "1",
            "Color": "YELLOW",
            "x": 100,
            "y":  -175,
            "Radius": 8,
            "Direction": -1.9,
            "AngularVelocity": -1,
            "CritRadiusMult": 1.3,
            "Velocity": 60
        },
        "Drifter": {
            "EnemyType": "1",
            "Color": "GREEN",
            "x": -120,
            "y": -80,
            "Radius": 10,
            "Direction": 3.92,
            "AngularVelocity": -1,
            "CritRadiusMult": 1.3,
            "Velocity": 50
        },
        "Drifter": {
            "EnemyType": "1",
            "Color": "GREEN",
            "x": -120,
            "y": -80,
            "Radius": 12,
            "Direction": 0.2,
            "AngularVelocity": -1,
            "CritRadiusMult": 1.2,
            "Velocity": 70
        },
        "Bullet": {
            "EnemyType": "3",
            "Color": "WHITE",
            "x": "115",
            "y": "-105",
            "Radius": 6,
            "FlickerRate": 1.2,
            "Direction": 1.6,
            "Velocity": 120
        },
        "Bullet": {
            "EnemyType": "3",
            "Color": "WHITE",
            "x": "-110",
            "y": "-105",
            "Radius": 7,
            "FlickerRate": 0.5,
            "Direction": -3.94,
            "Velocity": 100
        },
        "Bullet": {
            "EnemyType": "3",
            "Color": "WHITE",
            "x": "-80",
            "y": "-11",
            "Radius": 5,
            "FlickerRate": 0.2,
            "Direction": 3.94,
            "Velocity": 90
        },
        "Bullet": {
            "EnemyType": "3",
            "Color": "WHITE",
            "x": "200",
            "y": "105",
            "Radius": 4,
            "FlickerRate": 0.5,
            "Direction": -1.94,
            "Velocity": 189
        },
        "Bullet": {
            "EnemyType": "3",
            "Color": "WHITE",
            "x": "-80",
            "y": "105",
            "Radius": 4,
            "FlickerRate": 0.8,
            "Direction": -0.94,
            "Velocity": 150
        },
        "Bullet": {
            "EnemyType": "3",
            "Color": "WHITE",
            "x": "80",
            "y": "115",
            "Radius": 9,
            "FlickerRate": 0.5,
            "Direction": 3.1,
            "Velocity": 120
        },
        "Bullet": {
            "EnemyType": "3",
            "Color": "WHITE",
            "x": "-80",
            "y": "115",
            "Radius": 10,
            "FlickerRate": 0.5,
            "Direction": 3.1,
            "Velocity": 99
        },
        "Bullet": {
            "EnemyType": "3",
            "Color": "WHITE",
            "x": "150",
            "y": "-100",
            "Radius": 8,
            "FlickerRate": 0.8,
            "Direction": 3,
            "Velocity": 60
        },
        "Bullet": {
            "EnemyType": "3",
            "Color": "WHITE",
            "x": "-150",
            "y": "100",
            "Radius": 10,
            "FlickerRate": 0.8,
            "Direction": 2.5,
            "Velocity": 70
        },
        "Bullet": {
            "EnemyType": "3",
            "Color": "WHITE",
            "x": "70",
            "y": "-10",
            "Radius": 7,
            "FlickerRate": 0.4,
            "Direction": -1,
            "Velocity": 58
        },
    }
}